nbdev_template/__init__.py
nbdev_template/_nbdev.py
nbdev_template/utils.py
os_utilities/__init__.py
os_utilities/_nbdev.py
os_utilities/clean-filenames
os_utilities/docs.py
os_utilities/nb2script
os_utilities/patch_fastcore_script.py
os_utilities/script.py
os_utilities/utils.py
os_utilities-0.0.72.data/scripts/clean-filenames
os_utilities-0.0.72.data/scripts/nb2script
os_utilities-0.0.72.dist-info/LICENSE
os_utilities-0.0.72.dist-info/METADATA
os_utilities-0.0.72.dist-info/WHEEL
os_utilities-0.0.72.dist-info/entry_points.txt
os_utilities-0.0.72.dist-info/top_level.txt
os_utilities-0.0.72.dist-info/RECORD
