Metadata-Version: 2.1
Name: os-utilities
Version: 0.0.72
Summary: File system utilities. Standard python libs only
Home-page: https://github.com/rsomani95/os_utilities/tree/master/
Author: Rahul Somani
Author-email: rsomani95@gmail.com
License: Apache Software License 2.0
Keywords: OS utilities
Platform: UNKNOWN
Classifier: Development Status :: 3 - Alpha
Classifier: Intended Audience :: Developers
Classifier: License :: OSI Approved :: Apache Software License
Classifier: Natural Language :: English
Classifier: Programming Language :: Python :: 3.6
Classifier: Programming Language :: Python :: 3.7
Classifier: Programming Language :: Python :: 3.8
Requires-Python: >=3.6
